[
    {
        "album_title": "3° Último",
        "year": "2014",
        "album_record": "Kamika-z",
        "tracks": [
            {
                "name": "Sempre É o Momento",
                "url": "https://www.vagalume.com.br/tribo-da-periferia/sempre-e-o-momento.html"
            },
            {
                "name": "Moleque Business",
                "url": "https://www.vagalume.com.br/tribo-da-periferia/moleque-business.html"
            },
            {
                "name": "Hora do Rush",
                "url": "https://www.vagalume.com.br/tribo-da-periferia/hora-do-rush.html"
            },
            {
                "name": "Insônia (Part. Hungria Hip Hop)",
                "url": "https://www.vagalume.com.br/tribo-da-periferia/insonia-part-hungria-hip-hop.html"
            },
            {
                "name": "Não Sabia Que Era Tão Bom Assim",
                "url": "https://www.vagalume.com.br/tribo-da-periferia/nao-sabia-que-era-tao-bom-assim.html"
            },
            {
                "name": "Viva Comum",
                "url": "https://www.vagalume.com.br/tribo-da-periferia/viva-comum.html"
            },
            {
                "name": "Só diretoria",
                "url": "https://www.vagalume.com.br/tribo-da-periferia/so-diretoria.html"
            },
            {
                "name": "Valores",
                "url": "https://www.vagalume.com.br/tribo-da-periferia/valores.html"
            },
            {
                "name": "Ela Que Decide",
                "url": "https://www.vagalume.com.br/tribo-da-periferia/ela-que-decide.html"
            },
            {
                "name": "Você Me Fez Errar",
                "url": "https://www.vagalume.com.br/tribo-da-periferia/voce-me-fez-errar.html"
            },
            {
                "name": "Não Vale a Pena Ficar Louco de Problema",
                "url": "https://www.vagalume.com.br/tribo-da-periferia/nao-vale-a-pena-ficar-louco-de-problema.html"
            },
            {
                "name": "Déjá Vú",
                "url": "https://www.vagalume.com.br/tribo-da-periferia/djavu.html"
            },
            {
                "name": "História de Varios",
                "url": "https://www.vagalume.com.br/tribo-da-periferia/historia-de-varios.html"
            },
            {
                "name": "Flores",
                "url": "https://www.vagalume.com.br/tribo-da-periferia/flores.html"
            }
        ]
    },
    {
        "album_title": "2º Último",
        "year": "2013",
        "album_record": "Kamika-z",
        "tracks": [
            {
                "name": "Cruzes",
                "url": "https://www.vagalume.com.br/tribo-da-periferia/cruzes.html"
            },
            {
                "name": "Vida de Malandro",
                "url": "https://www.vagalume.com.br/tribo-da-periferia/vida-de-malandro.html"
            },
            {
                "name": "Pensem O Que Quiser",
                "url": "https://www.vagalume.com.br/tribo-da-periferia/pensem-o-que-quiser.html"
            },
            {
                "name": "Academia Kamika-Z",
                "url": "https://www.vagalume.com.br/tribo-da-periferia/academia-kamika-z.html"
            },
            {
                "name": "Aniversário do Colombiano",
                "url": "https://www.vagalume.com.br/tribo-da-periferia/aniversario-do-colombiano.html"
            },
            {
                "name": "Insaneou",
                "url": "https://www.vagalume.com.br/tribo-da-periferia/insaneou.html"
            },
            {
                "name": "Ela Tá Virada",
                "url": "https://www.vagalume.com.br/tribo-da-periferia/ela-ta-virada.html"
            },
            {
                "name": "Marciano (part. Diey)",
                "url": "https://www.vagalume.com.br/tribo-da-periferia/marciano-part-diey.html"
            },
            {
                "name": "Sem Esparrar",
                "url": "https://www.vagalume.com.br/tribo-da-periferia/sem-esparrar.html"
            },
            {
                "name": "Uns E Outros",
                "url": "https://www.vagalume.com.br/tribo-da-periferia/uns-e-outros.html"
            },
            {
                "name": "Acorda Cedo",
                "url": "https://www.vagalume.com.br/tribo-da-periferia/acorda-cedo.html"
            },
            {
                "name": "Essas Dona É Fight",
                "url": "https://www.vagalume.com.br/tribo-da-periferia/essas-dona-e-fight.html"
            },
            {
                "name": "Não Choro Mais (Part. Primo I)",
                "url": "https://www.vagalume.com.br/tribo-da-periferia/nao-choro-mais.html"
            },
            {
                "name": "Golfman",
                "url": "https://www.vagalume.com.br/tribo-da-periferia/golfman.html"
            },
            {
                "name": "Águas",
                "url": "https://www.vagalume.com.br/tribo-da-periferia/aguas.html"
            }
        ]
    },
    {
        "album_title": "1° Último",
        "year": "2011",
        "album_record": "Kamika-z",
        "tracks": [
            {
                "name": "Temperamento Emocional",
                "url": "https://www.vagalume.com.br/tribo-da-periferia/temperamento-emocional.html"
            },
            {
                "name": "Perigo Universal",
                "url": "https://www.vagalume.com.br/tribo-da-periferia/perigo-universal.html"
            },
            {
                "name": "Ex-Engraxate",
                "url": "https://www.vagalume.com.br/tribo-da-periferia/ex-engraxate.html"
            },
            {
                "name": "Hoje Vai Ter Cerol",
                "url": "https://www.vagalume.com.br/tribo-da-periferia/hoje-vai-ter-cerol.html"
            },
            {
                "name": "Depois Das Zero",
                "url": "https://www.vagalume.com.br/tribo-da-periferia/depois-das-zero.html"
            },
            {
                "name": "My House",
                "url": "https://www.vagalume.com.br/tribo-da-periferia/my-house.html"
            },
            {
                "name": "Você Quer",
                "url": "https://www.vagalume.com.br/tribo-da-periferia/voce-quer.html"
            },
            {
                "name": "Amnésia",
                "url": "https://www.vagalume.com.br/tribo-da-periferia/amnesia.html"
            },
            {
                "name": "Pode Olhar Que Eu Deixo",
                "url": "https://www.vagalume.com.br/tribo-da-periferia/pode-olhar-que-eu-deixo.html"
            },
            {
                "name": "Amor Criminal",
                "url": "https://www.vagalume.com.br/tribo-da-periferia/amor-criminal.html"
            },
            {
                "name": "Fico de Boa",
                "url": "https://www.vagalume.com.br/tribo-da-periferia/fico-de-boa.html"
            },
            {
                "name": "Absolve Ele (doutor Advogado)",
                "url": "https://www.vagalume.com.br/tribo-da-periferia/absolve-ele-doutor-advogado.html"
            }
        ]
    },
    {
        "album_title": "Tudo Nosso",
        "year": "2006",
        "album_record": "Kamika-z",
        "tracks": [
            {
                "name": "Tudo Nosso",
                "url": "https://www.vagalume.com.br/tribo-da-periferia/tudo-nosso.html"
            },
            {
                "name": "Carro de Malandro",
                "url": "https://www.vagalume.com.br/tribo-da-periferia/carro-de-malandro.html"
            },
            {
                "name": "Vagabundo Quer",
                "url": "https://www.vagalume.com.br/tribo-da-periferia/vagabundo-quer.html"
            },
            {
                "name": "A Vida Continua",
                "url": "https://www.vagalume.com.br/tribo-da-periferia/a-vida-continua.html"
            },
            {
                "name": "No Baile",
                "url": "https://www.vagalume.com.br/tribo-da-periferia/no-baile.html"
            },
            {
                "name": "Quem Tá Vivo Corre O Risco",
                "url": "https://www.vagalume.com.br/tribo-da-periferia/quem-ta-vivo-corre-o-risco.html"
            },
            {
                "name": "5 Conto leva a erva",
                "url": "https://www.vagalume.com.br/tribo-da-periferia/5-conto-leva-a-erva.html"
            },
            {
                "name": "Dublê da Covardia",
                "url": "https://www.vagalume.com.br/tribo-da-periferia/duble-da-covardia.html"
            },
            {
                "name": "Nos Bastidores da Vida Real",
                "url": "https://www.vagalume.com.br/tribo-da-periferia/nos-bastidores-da-vida-real.html"
            },
            {
                "name": "Um Sonho",
                "url": "https://www.vagalume.com.br/tribo-da-periferia/um-sonho.html"
            },
            {
                "name": "Se essa arma fosse minha",
                "url": "https://www.vagalume.com.br/tribo-da-periferia/se-essa-arma-fosse-minha.html"
            },
            {
                "name": "Marginal Protagonista",
                "url": "https://www.vagalume.com.br/tribo-da-periferia/marginal-protagonista.html"
            }
        ]
    },
    {
        "album_title": "Verdadeiro Brasileiro",
        "year": "2003",
        "album_record": null,
        "tracks": [
            {
                "name": "Prosa De Malandro",
                "url": "https://www.vagalume.com.br/tribo-da-periferia/prosa-de-malandro.html"
            },
            {
                "name": "Entre A Vida E A Morte",
                "url": "https://www.vagalume.com.br/tribo-da-periferia/entre-a-vida-e-a-morte.html"
            },
            {
                "name": "Entre A Vida E A Morte",
                "url": "https://www.vagalume.com.br/tribo-da-periferia/entre-a-vida-e-a-morte.html"
            },
            {
                "name": "Que O Bicho Vai Pegar",
                "url": "https://www.vagalume.com.br/tribo-da-periferia/que-o-bicho-vai-pegar.html"
            },
            {
                "name": "Que O Bicho Vai Pegar",
                "url": "https://www.vagalume.com.br/tribo-da-periferia/que-o-bicho-vai-pegar.html"
            },
            {
                "name": "Verdadeiro Brasileiro",
                "url": "https://www.vagalume.com.br/tribo-da-periferia/verdadeiro-brasileiro.html"
            },
            {
                "name": "Vivendo E Aprendendo",
                "url": "https://www.vagalume.com.br/tribo-da-periferia/vivendo-e-aprendendo.html"
            },
            {
                "name": "Vivendo E Aprendendo",
                "url": "https://www.vagalume.com.br/tribo-da-periferia/vivendo-e-aprendendo.html"
            },
            {
                "name": "Servo Da Guerra",
                "url": "https://www.vagalume.com.br/tribo-da-periferia/servo-da-guerra.html"
            },
            {
                "name": "Valorizando A Quebrada",
                "url": "https://www.vagalume.com.br/tribo-da-periferia/valorizando-a-quebrada.html"
            },
            {
                "name": "Valorizando A Quebrada",
                "url": "https://www.vagalume.com.br/tribo-da-periferia/valorizando-a-quebrada.html"
            },
            {
                "name": "Negreja",
                "url": "https://www.vagalume.com.br/tribo-da-periferia/negreja.html"
            },
            {
                "name": "Esperando A Morte Chegar",
                "url": "https://www.vagalume.com.br/tribo-da-periferia/esperando-a-morte-chegar.html"
            }
        ]
    }
]